PsychonautCrawler-1.0.2.data/scripts/run.py
psychonautcrawler/__init__.py
psychonautcrawler/crawler.py
PsychonautCrawler-1.0.2.dist-info/LICENSE
PsychonautCrawler-1.0.2.dist-info/METADATA
PsychonautCrawler-1.0.2.dist-info/WHEEL
PsychonautCrawler-1.0.2.dist-info/top_level.txt
PsychonautCrawler-1.0.2.dist-info/RECORD
