Metadata-Version: 2.1
Name: PsychonautCrawler
Version: 1.0.2
Summary: A crawler for PsychonautWiki wrote in python.
Home-page: https://github.com/BlakeBarnes00/PsychonautCrawler
Author: Ellis Barnes
Author-email: EllisBarnes00@gmail.com
License: This is free and unencumbered software released into the public domain.        
Project-URL: Bug Tracker, https://github.com/BlakeBarnes00/PsychonautCrawler/issues
Platform: UNKNOWN
Classifier: Development Status :: 2 - Pre-Alpha
Classifier: Environment :: Console
Classifier: Environment :: Web Environment
Classifier: Programming Language :: Python :: 3
Classifier: License :: OSI Approved :: The Unlicense (Unlicense)
Classifier: Operating System :: OS Independent
Classifier: Intended Audience :: Developers
Classifier: Intended Audience :: Science/Research
Requires-Python: >=3.6
License-File: LICENSE
